[
  {
    "id":"S12000033",
    "name":"Aberdeen City",
    "homepage":"http://www.aberdeencity.gov.uk/home/home.asp",
    "tax":"http://www.aberdeencity.gov.uk/business_trade/business_rates/bur_BusRates.asp"
  },
  {
    "id":"S12000034",
    "name":"Aberdeenshire",
    "homepage":"https://www.aberdeenshire.gov.uk/",
    "tax":"http://www.aberdeenshire.gov.uk/rates/"
  },
  {
    "id":"S12000041",
    "name":"Angus",
    "homepage":"http://www.angus.gov.uk/",
    "tax":"http://www.angus.gov.uk/info/20132/business_rates"
  },
  {
    "id":"S12000035",
    "name":"Argyll and Bute",
    "homepage":"http://www.argyll-bute.gov.uk/home",
    "tax":"http://www.argyll-bute.gov.uk/business-and-trade/business-rates"
  },
  {
    "id":"S12000005",
    "name":"Clackmannanshire",
    "homepage":"http://www.clacksweb.org.uk/",
    "tax":"http://www.clacksweb.org.uk/council/payit/"
  },
  {
    "id":"S12000006",
    "name":"Dumfries and Galloway",
    "homepage":"http://www.dumgal.gov.uk/",
    "tax":"http://www.dumgal.gov.uk/index.aspx?articleid=1120"
  },
  {
    "id":"S12000042",
    "name":"City of Dundee",
    "homepage":"http://www.dundeecity.gov.uk/",
    "tax":"http://www.dundeecity.gov.uk/finance/nondomesticrates/"
  },
  {
    "id":"S12000008",
    "name":"East Ayrshire",
    "homepage":"http://www.east-ayrshire.gov.uk/Home.aspx",
    "tax":"http://www.east-ayrshire.gov.uk/BusinessAndTrade/BusinessRates/BusinessRates.aspx"
  },
  {
    "id":"S12000039",
    "name":"East Dunbartonshire",
    "homepage":"http://www.eastdunbarton.gov.uk/home.aspx",
    "tax":"http://www.eastdunbarton.gov.uk/default.aspx?page=14523"
  },
  {
    "id":"S12000010",
    "name":"East Lothian",
    "homepage":"http://www.eastlothian.gov.uk/",
    "tax":"http://www.eastlothian.gov.uk/info/2/business_rates/539/business_rates/5"
  },
  {
    "id":"S12000011",
    "name":"East Renfrewshire",
    "homepage":"http://www.eastrenfrewshire.gov.uk/home",
    "tax":"http://www.eastrenfrewshire.gov.uk/business_rates"
  },
  {
    "id":"S12000036",
    "name":"City of Edinburgh",
    "homepage":"http://www.edinburgh.gov.uk/",
    "tax":"http://www.edinburgh.gov.uk/info/20020/business_rates/757/non-domestic_business_rates_charges"
  },
  {
    "id":"S12000013",
    "name":"Comhairle nan Eilean Siar (Outer Hebrides)",
    "homepage":"http://www.cne-siar.gov.uk/",
    "tax":"http://www.cne-siar.gov.uk/rates/"
  },
  {
    "id":"S12000014",
    "name":"Falkirk",
    "homepage":"https://www.falkirk.gov.uk/",
    "tax":"https://www.falkirk.gov.uk/services/business-investment/business-rates/"
  },
  {
    "id":"S12000015",
    "name":"Fife",
    "homepage":"http://www.fifedirect.org.uk/",
    "tax":"http://www.fife.gov.uk/topics/index.cfm?fuseaction=subject.display&subjectid=350F6121-ADF3-2158-7D94B34548B73EED"
  },
  {
    "id":"S12000046",
    "name":"Glasgow",
    "homepage":"https://www.glasgow.gov.uk/",
    "tax":"https://www.glasgow.gov.uk/index.aspx?articleid=3165"
  },
  {
    "id":"S12000017",
    "name":"Highland",
    "homepage":"http://www.highland.gov.uk/",
    "tax":"http://www.highland.gov.uk/info/2/business_rates/404/non-domestic_rates"
  },
  {
    "id":"S12000018",
    "name":"Inverclyde",
    "homepage":"http://www.inverclyde.gov.uk/",
    "tax":"http://www.inverclyde.gov.uk/council-and-government/non-domestic-rates"
  },
  {
    "id":"S12000019",
    "name":"Midlothian",
    "homepage":"http://www.midlothian.gov.uk/",
    "tax":"http://www.midlothian.gov.uk/info/2/business_rates"
  },
  {
    "id":"S12000020",
    "name":"Moray",
    "homepage":"http://www.moray.gov.uk/",
    "tax":"http://www.moray.gov.uk/moray_standard/page_2272.html"
  },
  {
    "id":"S12000021",
    "name":"North Ayrshire",
    "homepage":"http://www.north-ayrshire.gov.uk/home.aspx",
    "tax":"http://www.north-ayrshire.gov.uk/business/business-rates/business-rates.aspx"
  },
  {
    "id":"S12000029",
    "name":"North Lanarkshire",
    "homepage":"http://www.northlanarkshire.gov.uk/",
    "tax":"http://www.northlanarkshire.gov.uk/index.aspx?articleid=29202"
  },
  {
    "id":"S12000023",
    "name":"Orkney",
    "homepage":"http://www.orkney.gov.uk/",
    "tax":"http://www.orkney.gov.uk/Service-Directory/B/Business-Rates.htm"
  },
  {
    "id":"S12000024",
    "name":"Perth and Kinross",
    "homepage":"http://www.pkc.gov.uk/",
    "tax":"http://www.pkc.gov.uk/article/1627/Business-rates"
  },
  {
    "id":"S12000038",
    "name":"Renfrewshire",
    "homepage":"http://www.renfrewshire.gov.uk/webcontent/home/",
    "tax":"http://www.renfrewshire.gov.uk/webcontent/home/Services/Business/Business+Rates/"
  },
  {
    "id":"S12000026",
    "name":"Scottish Borders",
    "homepage":"http://www.scotborders.gov.uk/",
    "tax":"http://www.scotborders.gov.uk/info/2/business_rates"
  },
  {
    "id":"S12000027",
    "name":"Shetland",
    "homepage":"http://www.shetland.gov.uk/",
    "tax":"http://www.shetland.gov.uk/about_business_rates/"
  },
  {
    "id":"S12000028",
    "name":"South Ayrshire",
    "homepage":"http://www.south-ayrshire.gov.uk/",
    "tax":"http://www.south-ayrshire.gov.uk/businessrates/"
  },
  {
    "id":"S12000029",
    "name":"South Lanarkshire",
    "homepage":"http://www.southlanarkshire.gov.uk/",
    "tax":"http://www.southlanarkshire.gov.uk/info/200157/business_rates"
  },
  {
    "id":"S12000030",
    "name":"Stirling",
    "homepage":"http://my.stirling.gov.uk/home?theme=MyStirling",
    "tax":"http://my.stirling.gov.uk/services/business-and-trade/business-rates?theme=MyStirling"
  },
  {
    "id":"S12000039",
    "name":"West Dunbartonshire",
    "homepage":"https://www.west-dunbarton.gov.uk/",
    "tax":"https://www.west-dunbarton.gov.uk/business/business-rates/business-rates/"
  },
  {
    "id":"S12000040",
    "name":"West Lothian",
    "homepage":"http://www.westlothian.gov.uk/",
    "tax":"http://www.westlothian.gov.uk/business-rates"
  }
]
